tinycarlo/__init__.py
tinycarlo/camera.py
tinycarlo/car.py
tinycarlo/env.py
tinycarlo/renderer.py
tinycarlo/reward_handler.py
tinycarlo/track.py
tinycarlo-1.1.dist-info/LICENSE
tinycarlo-1.1.dist-info/METADATA
tinycarlo-1.1.dist-info/WHEEL
tinycarlo-1.1.dist-info/top_level.txt
tinycarlo-1.1.dist-info/RECORD
