Metadata-Version: 2.1
Name: tinycarlo
Version: 1.1
Summary: 2D car simulation
Home-page: https://github.com/danielriege/tinycarlo
Author: Daniel Riege, Markus Kasten
License: UNKNOWN
Platform: UNKNOWN
License-File: LICENSE
Requires-Dist: gym (>=0.21.0)
Requires-Dist: numpy (>=1.22.0)
Requires-Dist: opencv-python (>=4.5.5.62)
Requires-Dist: setuptools (>=60.3.1)
Requires-Dist: pyyaml (>=6.0)
